cvextend/__init__.py
cvextend/_version.py
cvextend/cv_wrappers.py
cvextend/eval_grid.py
cvextend/param_grid.py
cvextend/score_grid.py
cvextend-0.2.2.dist-info/LICENSE
cvextend-0.2.2.dist-info/METADATA
cvextend-0.2.2.dist-info/WHEEL
cvextend-0.2.2.dist-info/top_level.txt
cvextend-0.2.2.dist-info/RECORD
