Metadata-Version: 2.1
Name: cvextend
Version: 0.2.2
Summary: Tools to extend sklearn's cross-validation classes and functions
Home-page: https://github.com/ldanov/pypkg_cvextend
Author: Lyubomir Danov
License: UNKNOWN
Platform: UNKNOWN
Requires-Dist: pandas (>=0.24.1)
Requires-Dist: scikit-learn (>=0.21.1)
